<annotation>
	<folder>CANNES_TILES_512x512</folder>
	<filename>CANNES_TILES_512x512.650.tif</filename>
	<path>F:\CANNES_TILES_512x512\CANNES_TILES_512x512.650.tif</path>
	<source>
		<database>Unknown</database>
	</source>
	<size>
		<width>512</width>
		<height>512</height>
		<depth>3</depth>
	</size>
	<segmented>0</segmented>
	<object>
		<name>pool</name>
		<pose>Unspecified</pose>
		<truncated>0</truncated>
		<difficult>0</difficult>
		<bndbox>
			<xmin>139</xmin>
			<ymin>445</ymin>
			<xmax>209</xmax>
			<ymax>496</ymax>
		</bndbox>
	</object>
	<object>
		<name>pool</name>
		<pose>Unspecified</pose>
		<truncated>0</truncated>
		<difficult>0</difficult>
		<bndbox>
			<xmin>275</xmin>
			<ymin>267</ymin>
			<xmax>320</xmax>
			<ymax>334</ymax>
		</bndbox>
	</object>
	<object>
		<name>pool</name>
		<pose>Unspecified</pose>
		<truncated>0</truncated>
		<difficult>0</difficult>
		<bndbox>
			<xmin>93</xmin>
			<ymin>125</ymin>
			<xmax>124</xmax>
			<ymax>168</ymax>
		</bndbox>
	</object>
	<object>
		<name>pool</name>
		<pose>Unspecified</pose>
		<truncated>0</truncated>
		<difficult>0</difficult>
		<bndbox>
			<xmin>320</xmin>
			<ymin>52</ymin>
			<xmax>357</xmax>
			<ymax>85</ymax>
		</bndbox>
	</object>
	<object>
		<name>pool</name>
		<pose>Unspecified</pose>
		<truncated>0</truncated>
		<difficult>0</difficult>
		<bndbox>
			<xmin>397</xmin>
			<ymin>399</ymin>
			<xmax>441</xmax>
			<ymax>453</ymax>
		</bndbox>
	</object>
	<object>
		<name>pool</name>
		<pose>Unspecified</pose>
		<truncated>0</truncated>
		<difficult>0</difficult>
		<bndbox>
			<xmin>473</xmin>
			<ymin>259</ymin>
			<xmax>490</xmax>
			<ymax>311</ymax>
		</bndbox>
	</object>
</annotation>
