<annotation>
	<folder>CANNES_TILES_512x512</folder>
	<filename>CANNES_TILES_512x512.381.tif</filename>
	<path>F:\CANNES_TILES_512x512\CANNES_TILES_512x512.381.tif</path>
	<source>
		<database>Unknown</database>
	</source>
	<size>
		<width>512</width>
		<height>512</height>
		<depth>3</depth>
	</size>
	<segmented>0</segmented>
	<object>
		<name>pool</name>
		<pose>Unspecified</pose>
		<truncated>0</truncated>
		<difficult>0</difficult>
		<bndbox>
			<xmin>162</xmin>
			<ymin>466</ymin>
			<xmax>218</xmax>
			<ymax>503</ymax>
		</bndbox>
	</object>
	<object>
		<name>pool</name>
		<pose>Unspecified</pose>
		<truncated>0</truncated>
		<difficult>0</difficult>
		<bndbox>
			<xmin>62</xmin>
			<ymin>398</ymin>
			<xmax>97</xmax>
			<ymax>436</ymax>
		</bndbox>
	</object>
	<object>
		<name>pool</name>
		<pose>Unspecified</pose>
		<truncated>0</truncated>
		<difficult>0</difficult>
		<bndbox>
			<xmin>301</xmin>
			<ymin>16</ymin>
			<xmax>344</xmax>
			<ymax>66</ymax>
		</bndbox>
	</object>
</annotation>
